ab/__init__.py
ab/rag/__init__.py
ab/rag/__main__.py
ab/rag/block_validator.py
ab/rag/cli.py
ab/rag/extract_blocks.py
ab/rag/file_index.py
ab/rag/make_blocks_name.py
ab/rag/models.py
ab/rag/config/__init__.py
ab/rag/config/config.py
ab/rag/utils/__init__.py
ab/rag/utils/compile_blocks.py
ab/rag/utils/definition_resolver.py
ab/rag/utils/path_resolver.py
ab/rag/utils/repo_cache.py
nn_rag-2.2.4.dist-info/licenses/LICENSE
tests/README.md
tests/__init__.py
tests/conftest.py
tests/run_tests.py
tests/rag/__init__.py
tests/rag/test_block_extractor.py
tests/rag/test_cli_consistency.py
tests/rag/test_error_scenarios.py
tests/rag/test_integration.py
tests/rag/test_performance.py
tests/rag/test_simple.py
tests/rag/test_validation.py
nn_rag-2.2.4.dist-info/METADATA
nn_rag-2.2.4.dist-info/WHEEL
nn_rag-2.2.4.dist-info/top_level.txt
nn_rag-2.2.4.dist-info/RECORD
