Metadata-Version: 2.4
Name: nn-rag
Version: 2.2.4
Summary: Neural Retrieval-Augmented Generation for GitHub code blocks
Author-email: ABrain One and contributors <AI@ABrain.one>
License: MIT License
Project-URL: Homepage, https://ABrain.one
Project-URL: Repository, https://github.com/ABrain-One/nn-rag
Project-URL: Bug Tracker, https://github.com/ABrain-One/nn-rag/issues
Keywords: retrieval-augmented generation,RAG,large language model,LLM,code blocks,neural retrieval,generation pipeline,vector search,indexing,Python,faiss,block extraction,GitHub code,contextual embedding
Classifier: Programming Language :: Python :: 3
Classifier: License :: OSI Approved :: MIT License
Classifier: Operating System :: OS Independent
Classifier: Topic :: Software Development :: Libraries
Classifier: Topic :: Scientific/Engineering :: Artificial Intelligence
Classifier: Topic :: Scientific/Engineering :: Information Analysis
Classifier: Intended Audience :: Developers
Classifier: Intended Audience :: Science/Research
Requires-Python: >=3.6
License-File: LICENSE
Requires-Dist: libcst>=1.0.0
Requires-Dist: tqdm>=4.65.0
Dynamic: license-file
